<?xml version="1.0" encoding="utf-8"?>
<TextureAtlas imagePath="FreeplayNorm.png">
	<!-- Created with Adobe Animate version 21.0.0.35450 -->
	<!-- http://www.adobe.com/products/animate.html -->
	<SubTexture name="freeplay norm0000" x="5" y="5" width="561" height="293"/>
	<SubTexture name="freeplay select0000" x="573" y="5" width="1274" height="524"/>
	<SubTexture name="freeplay select0001" x="573" y="5" width="1274" height="524"/>
	<SubTexture name="freeplay select0002" x="573" y="5" width="1274" height="524"/>
	<SubTexture name="freeplay select0003" x="5" y="536" width="1274" height="524"/>
	<SubTexture name="freeplay select0004" x="5" y="536" width="1274" height="524"/>
	<SubTexture name="freeplay select0005" x="5" y="536" width="1274" height="524"/>
	<SubTexture name="freeplay select0006" x="5" y="1067" width="1274" height="524"/>
	<SubTexture name="freeplay select0007" x="5" y="1067" width="1274" height="524"/>
	<SubTexture name="freeplay select0008" x="5" y="1067" width="1274" height="524"/>
</TextureAtlas>
